{
  "version": 1,
  "serviceConfiguration": {
    "apiName": "haliv7",
    "serviceName": "AppSync",
    "gqlSchemaPath": "/tmp/amplify-5982268d-e1be-44a6-8b41-a1eff3a7ef22/amplify/backend/api/haliv7/schema.graphql",
    "defaultAuthType": {
      "mode": "AMAZON_COGNITO_USER_POOLS",
      "cognitoUserPoolId": "authhaliv7"
    },
    "conflictResolution": {
      "defaultResolutionStrategy": {
        "type": "AUTOMERGE"
      }
    },
    "additionalAuthTypes": [
      {
        "mode": "AWS_IAM"
      }
    ]
  }
}